datastructures/Linear/CDLL.py
datastructures/Linear/CSLL.py
datastructures/Linear/DLL.py
datastructures/Linear/LLQueue.py
datastructures/Linear/LLStack.py
datastructures/Linear/SLL.py
datastructures/Linear/__init__.py
datastructures/Nodes/DNode.py
datastructures/Nodes/TNode.py
datastructures/Nodes/__init__.py
datastructures/Trees/AVL.py
datastructures/Trees/BST.py
datastructures/Trees/__init__.py
datastructuresLionelEric-2.44.dist-info/METADATA
datastructuresLionelEric-2.44.dist-info/WHEEL
datastructuresLionelEric-2.44.dist-info/top_level.txt
datastructuresLionelEric-2.44.dist-info/RECORD
