Metadata-Version: 2.1
Name: datastructuresLionelEric
Version: 2.44
Summary: My first Python library
Author: Me
License: MIT
